PY_GUI/__init__.py
PY_GUI/__main__.py
PY_GUI-1.0.4.dist-info/LICENSE
PY_GUI-1.0.4.dist-info/METADATA
PY_GUI-1.0.4.dist-info/WHEEL
PY_GUI-1.0.4.dist-info/entry_points.txt
PY_GUI-1.0.4.dist-info/top_level.txt
PY_GUI-1.0.4.dist-info/RECORD
