Metadata-Version: 2.1
Name: PY-GUI
Version: 1.0.4
Summary: Create a pygame session for specific functions
Home-page: https://github.com/donno2048/PY-GUI
Author: Elisha Hollander
License: MIT
Classifier: Programming Language :: Python :: 3
License-File: LICENSE
Requires-Dist: pygame (>=2.0.0)
Requires-Dist: pygame-gui (>=0.5.7)
